simplesimplestreams/__init__.py
simplesimplestreams/py.typed
simplesimplestreams/simplestreams.py
simplesimplestreams-0.1.1.dist-info/LICENSE
simplesimplestreams-0.1.1.dist-info/WHEEL
simplesimplestreams-0.1.1.dist-info/METADATA
simplesimplestreams-0.1.1.dist-info/RECORD
