Metadata-Version: 2.1
Name: simplesimplestreams
Version: 0.1.1
Summary: simple simplestreams client
Home-page: https://github.com/otariidae/simplesimplestreams
License: Apache-2.0
Author: otariidae
Author-email: otariidae@users.noreply.github.com
Requires-Python: >=3.9,<4.0
Classifier: License :: OSI Approved :: Apache Software License
Classifier: Programming Language :: Python :: 3
Classifier: Programming Language :: Python :: 3.9
Requires-Dist: requests (>=2.26.0,<3.0.0)
Project-URL: Repository, https://github.com/otariidae/simplesimplestreams
